{"totalCount":52801,"generateTime":"2026-07-12 20:02:01","data":[{"recipe":[250,230,30,30,1],"count":1,"usedCount":61,"hqLvCount":{"120":1},"secretaryCount":{"第三〇号海防艦改":1},"kdockCount":{"3":1},"rate":1.639},{"recipe":[30,30,120,30,1],"count":1,"usedCount":10,"hqLvCount":{"110":1},"secretaryCount":{"三隈改":1},"kdockCount":{"2":1},"rate":10.0},{"recipe":[30,30,100,30,1],"count":1,"usedCount":7,"hqLvCount":{"108":1},"secretaryCount":{"Gotland andra":1},"kdockCount":{"2":1},"rate":14.286},{"recipe":[200,30,210,30,1],"count":1,"usedCount":2,"hqLvCount":{"109":1},"secretaryCount":{"矢矧改二乙":1},"kdockCount":{"2":1},"rate":50.0},{"recipe":[230,130,200,30,1],"count":1,"usedCount":12,"hqLvCount":{"120":1},"secretaryCount":{"鹿島改":1},"kdockCount":{"2":1},"rate":8.333},{"recipe":[30,30,40,30,1],"count":1,"usedCount":76,"hqLvCount":{"100":1},"secretaryCount":{"翔鶴":1},"kdockCount":{"2":1},"rate":1.316},{"recipe":[230,230,230,130,1],"count":2,"usedCount":17,"hqLvCount":{"120":1,"13":1},"secretaryCount":{"大和改二重":1,"吹雪":1},"kdockCount":{"2":2},"rate":11.765},{"recipe":[30,70,30,70,1],"count":1,"usedCount":1,"hqLvCount":{"6":1},"secretaryCount":{"多摩":1},"kdockCount":{"2":1},"rate":100.0},{"recipe":[30,140,30,30,1],"count":2,"usedCount":7,"hqLvCount":{"80":2},"secretaryCount":{"暁改二":2},"kdockCount":{"2":2},"rate":28.571},{"recipe":[200,300,200,30,1],"count":2,"usedCount":2,"hqLvCount":{"120":2},"secretaryCount":{"Nelson改":2},"kdockCount":{"4":2},"rate":100.0},{"recipe":[300,400,30,301,1],"count":2,"usedCount":5,"hqLvCount":{"64":2},"secretaryCount":{"雪風改":2},"kdockCount":{"2":2},"rate":40.0},{"recipe":[30,430,30,30,1],"count":2,"usedCount":3,"hqLvCount":{"60":2},"secretaryCount":{"暁":2},"kdockCount":{"2":2},"rate":66.667},{"recipe":[300,401,30,301,1],"count":3,"usedCount":58,"hqLvCount":{"38":2,"34":1},"secretaryCount":{"翔鶴改":2,"伊勢改":1},"kdockCount":{"2":3},"rate":5.172},{"recipe":[30,999,30,999,1],"count":1,"usedCount":28,"hqLvCount":{"120":1},"secretaryCount":{"浜波改二":1},"kdockCount":{"2":1},"rate":3.571},{"recipe":[30,300,400,300,1],"count":1,"usedCount":4,"hqLvCount":{"120":1},"secretaryCount":{"矢矧改二乙":1},"kdockCount":{"2":1},"rate":25.0},{"recipe":[30,30,430,30,1],"count":1,"usedCount":12,"hqLvCount":{"120":1},"secretaryCount":{"加賀改二":1},"kdockCount":{"2":1},"rate":8.333},{"recipe":[30,90,90,30,1],"count":1,"usedCount":2,"hqLvCount":{"45":1},"secretaryCount":{"赤城改":1},"kdockCount":{"2":1},"rate":50.0},{"recipe":[30,30,30,130,1],"count":1,"usedCount":49,"hqLvCount":{"119":1},"secretaryCount":{"Gloire改":1},"kdockCount":{"2":1},"rate":2.041},{"recipe":[130,130,30,30,1],"count":2,"usedCount":52,"hqLvCount":{"113":1,"120":1},"secretaryCount":{"Maryland改":1,"山汐丸改":1},"kdockCount":{"4":1,"2":1},"rate":3.846},{"recipe":[50,50,50,40,1],"count":1,"usedCount":2,"hqLvCount":{"120":1},"secretaryCount":{"長波改二":1},"kdockCount":{"2":1},"rate":50.0},{"recipe":[60,60,60,60,1],"count":1,"usedCount":16,"hqLvCount":{"111":1},"secretaryCount":{"明石改":1},"kdockCount":{"2":1},"rate":6.25},{"recipe":[31,30,31,31,1],"count":1,"usedCount":1,"hqLvCount":{"97":1},"secretaryCount":{"暁改二":1},"kdockCount":{"2":1},"rate":100.0},{"recipe":[50,50,50,50,1],"count":5,"usedCount":192,"hqLvCount":{"2":1,"101":2,"100":2},"secretaryCount":{"電":1,"瑞鶴改":1,"陸奥改":1,"松輪改":1,"長門改":1},"kdockCount":{"2":5},"rate":2.604},{"recipe":[30,30,30,35,1],"count":2,"usedCount":6,"hqLvCount":{"120":2},"secretaryCount":{"三隈改二特":2},"kdockCount":{"2":2},"rate":33.333},{"recipe":[40,230,60,130,1],"count":1,"usedCount":1,"hqLvCount":{"67":1},"secretaryCount":{"千歳甲":1},"kdockCount":{"2":1},"rate":100.0},{"recipe":[30,250,250,30,1],"count":1,"usedCount":33,"hqLvCount":{"120":1},"secretaryCount":{"長門改二":1},"kdockCount":{"4":1},"rate":3.03},{"recipe":[30,30,999,30,1],"count":22,"usedCount":1229,"hqLvCount":{"120":17,"112":1,"119":1,"103":1,"109":2},"secretaryCount":{"大鳳改":2,"大和改二":1,"加賀改二護":1,"秋月":1,"秋月改二":1,"榛名改二丙":2,"海風改二":1,"藤波改二":1,"加賀改二":1,"翔鶴改二甲":1,"矢矧改二乙":1,"秋月改":2,"薄雲":1,"朧改":1,"天城改":2,"明石改":2,"狭霧改":1},"kdockCount":{"2":12,"3":7,"4":3},"rate":1.79},{"recipe":[30,30,30,30,1],"count":52585,"usedCount":2644365,"hqLvCount":{"100":320,"108":627,"113":820,"116":845,"118":774,"120":38383,"102":264,"117":809,"101":342,"105":494,"103":411,"112":776,"109":748,"111":796,"119":830,"106":549,"110":801,"94":32,"98":184,"99":302,"114":783,"115":837,"33":2,"81":10,"107":601,"104":377,"16":4,"87":21,"47":10,"29":2,"97":108,"96":67,"74":11,"95":38,"75":17,"25":5,"55":3,"12":4,"37":2,"59":13,"84":17,"79":6,"90":16,"19":4,"83":25,"68":9,"86":13,"85":11,"78":25,"80":11,"15":4,"64":9,"41":5,"3":8,"89":26,"48":6,"1":6,"92":20,"57":4,"43":4,"49":5,"52":8,"40":5,"91":13,"73":7,"42":2,"5":3,"58":5,"54":4,"35":2,"61":6,"38":5,"76":11,"82":11,"70":13,"63":11,"77":6,"65":8,"62":11,"66":7,"2":3,"8":6,"93":24,"60":5,"20":4,"56":8,"6":4,"69":9,"13":2,"21":3,"14":5,"4":8,"9":3,"51":6,"88":13,"17":6,"67":10,"44":4,"10":3,"46":5,"72":7,"71":7,"39":3,"22":1,"53":2,"23":6,"27":1,"45":2,"26":5,"36":5,"24":4,"30":3,"31":2,"50":3,"34":2,"7":2,"11":3,"28":2},"secretaryCount":{"瑞鶴改":80,"あきつ丸改":220,"大鯨":69,"明石改":2610,"飛龍改二":524,"伊13改":116,"翔鶴改二甲":1285,"瑞鶴改二甲":1801,"長門改二":900,"文月改二":38,"赤城改二戊":598,"加賀改二":714,"Richard P.Leary改":228,"大和改二":1175,"Richard P.Leary":153,"藤波改二":269,"Saratoga Mk.II Mod.2":132,"龍鳳改二戊":234,"龍鳳改":60,"Commandant Teste改":1142,"第百一号輸送艦":28,"武蔵改二":1444,"まるゆ改":51,"加賀改二戊":284,"Heywood L.E.":36,"島風改":72,"金剛改二丙":844,"睦月改":36,"時雨改三":626,"香取改":104,"天津風改":167,"Bismarck drei":147,"天霧改":47,"榧改":49,"鳥海改二":19,"瑞鳳改二乙":833,"稲木改二":53,"神州丸改":338,"熊野丸改":43,"しまね丸改":77,"比叡改二丙":173,"玉波改":134,"朝霜":11,"漣改":39,"大淀改":192,"平安丸改":32,"Warspite改":224,"Gloire改":42,"大鳳改":1478,"球磨改二":10,"翔鶴改":86,"榛名改二":132,"夕雲改二":37,"Washington改":25,"伊19改":85,"榛名改二丙":239,"秋月改":386,"Gambier Bay":31,"神州丸":102,"瑞鶴改二":22,"日向改二":363,"翔鶴":28,"村雨改":19,"Lexington改":45,"Gambier Bay Mk.II":87,"五十鈴改二":68,"金剛改":56,"龍驤改二":67,"叢雲改二":70,"初月":19,"Nelson改":939,"村雨改二":88,"矢矧改二乙":664,"大泊":48,"Maestrale":2,"Верный":148,"Phoenix":30,"Glorious":109,"Bismarck改":10,"赤城改二":649,"伊504":48,"初月改二":676,"Valiant":84,"榛名改二乙":375,"赤城改":210,"雲龍改":71,"Saratoga":23,"神威":24,"Ташкент":23,"国後改":24,"鳥海改":26,"暁改二":18,"Johnston改":76,"伊203":41,"大和改二重":617,"白露改二":31,"三隈改二":10,"Wasp改":143,"潮":5,"Richelieu改":68,"Salmon改":50,"日向改":129,"Fletcher":42,"Scamp改":196,"Glorious改":118,"Киров":53,"海風":4,"Hornet改":51,"日進甲":88,"迅鯨改":104,"野埼":348,"如月改二":47,"長門":12,"Ranger改":72,"Helena改":23,"飛龍":36,"満潮改二":52,"清霜改二丁":17,"鹿島":10,"霞改二乙":22,"球磨改二丁":10,"野埼改":266,"電改":85,"しまね丸":43,"秋月":47,"鳳翔改":102,"飛龍改三":438,"川内改二":201,"由良改二":70,"旗風改":11,"Киров改":79,"神通改二":38,"初霜改":14,"時雨改":27,"熊野改":24,"時雨改二":156,"伊勢改二":709,"Nevada改 Mod.2":39,"Drum改":25,"伊401":6,"伊203改":81,"UIT-24":9,"伊201改":92,"Nevada改":24,"第四号海防艦":19,"川内改":19,"藤波改":59,"伊400改":33,"早波改二":117,"大和":207,"瑞穂":17,"榛名改":39,"瑞鳳":24,"伊47改":97,"鳳翔改二":148,"Leonardo da Vinci":58,"神風改":131,"最上改":45,"伊14改":68,"伊8改":70,"大和改":180,"冬月":33,"長波改二":150,"加賀改二護":133,"Northampton改":31,"浜波改":94,"白露改":35,"能代改二":108,"夕立改二":242,"巻雲改":13,"Gotland":40,"三隈改":50,"浜波改二":137,"浦風丁改":20,"北上":32,"白雪改":57,"伊401改":48,"比叡改":13,"秋雲改":22,"鳳翔":14,"利根改二":20,"三隈改二特":86,"UIT-25":12,"Tuscaloosa改":28,"蒼龍改二":251,"雷":5,"春雨改二":77,"Minneapolis改":124,"明石":107,"蒼龍改":53,"由良改":39,"翔鶴改二":42,"天城改":43,"第三〇号海防艦":16,"長門改":43,"雪風改二":322,"朝日":33,"霞改二":148,"Richelieu Deux":295,"曙改二":55,"鹿島改":176,"早潮改":26,"妙高改二":45,"樫改":43,"鈴谷改二":18,"秋月改二":292,"Libeccio改":14,"Mogador":32,"樫":27,"Mogador改":114,"Norge改":47,"Heywood L.E.改":47,"Thonburi改":90,"萩風改":16,"利根改":4,"矢矧改二":14,"朝日改":51,"吹雪改三護(六式)":87,"夕張改二":3,"天津風改二":195,"涼波改二":49,"択捉改":34,"子日改":12,"如月":3,"名取改":15,"祥鳳改":67,"春雨改":33,"金剛改二":140,"夕張改":64,"浜風改":9,"磯風改":17,"水無月改":22,"伊168改":61,"吹雪改二":244,"Gotland andra":72,"秋霜改":42,"Jean Bart改":98,"熊野丸":18,"夕暮":8,"熊野改二":13,"Northampton":10,"早霜改二":22,"桃":5,"早潮改二":32,"対馬改":27,"初春改二":15,"伊26":5,"Phoenix改":37,"陸奥改":56,"呂500":115,"涼月改":122,"夕張改二特":156,"Graf Zeppelin改":75,"高波改二":15,"卯月改":41,"昭南改":13,"丹陽":42,"瑞鳳改":62,"如月改":12,"旗風":3,"Langley改":81,"伊58改":175,"浜風乙改":36,"蒼龍":16,"Saratoga Mk.II":61,"霧島改二丙":174,"巻波":9,"Z1 zwei":14,"朝潮改二丁":92,"Gotland改":44,"照月改":86,"暁改":17,"陸奥改二":190,"Wahoo":77,"大鷹改二":40,"能代改":38,"矢矧改":157,"Zara":4,"矢矧":49,"杉改":56,"武蔵":70,"朝風改":14,"飛龍改":71,"Norge":52,"秋雲改二":46,"野分改":22,"あきつ丸":27,"宗谷":204,"龍鳳改二":189,"大潮改二":16,"天霧":16,"北上改":61,"Roma":16,"早波改":117,"Maryland改":14,"妙高改":8,"Iowa改":148,"伊47":18,"天龍改":32,"朧改":37,"江風改":22,"Warspite":55,"浦風改":9,"綾波改二":76,"Javelin改":47,"隼鷹改二":60,"嵐改":10,"吹雪改":85,"まるゆ":64,"第三〇号海防艦改":35,"吹雪改三":35,"松輪":8,"Rodney改":163,"Dace改":89,"薄雲":7,"武蔵改":90,"沖波改二":8,"Ranger":13,"球磨":3,"三隈":86,"天津風":39,"雲鷹改":49,"深雪改二":113,"冬月改":93,"最上改二特":79,"伊36改":31,"龍田改二":14,"峯雲改":11,"鵜来改":66,"Johnston":77,"睦月改二":99,"対馬":18,"松輪改":32,"綾波改":18,"千歳甲":24,"浦波改":14,"Tuscaloosa":25,"飛鷹改":42,"Wahoo改":109,"大泊改":44,"伊勢改":91,"山汐丸改":129,"秋津洲改":25,"Intrepid改":74,"Wasp":75,"Saratoga改":58,"South Dakota改":25,"Ark Royal改":201,"Prinz Eugen改":26,"Fletcher Mk.II":101,"初雪改":64,"初雪改二":25,"石垣改":22,"雲鷹":36,"福江改":16,"Dace":62,"Scamp":33,"風雲":7,"雪風改":82,"Zara due":26,"瑞鳳改二":30,"長鯨":18,"Fletcher改 Mod.2":24,"第四号海防艦改":37,"Eidsvold改":32,"磯風":13,"千歳":10,"千歳航改二":50,"Grecale改":19,"第二十二号海防艦改":30,"玉波":7,"U-511改":12,"阿武隈改二":110,"山汐丸":18,"天霧改二丁":24,"八丈改":29,"Thonburi":58,"八幡丸":19,"Washington":3,"平戸":10,"千代田航":7,"Gambier Bay改":54,"谷風改":9,"神風":27,"霧島改二":32,"潮改二":73,"伊503":29,"加賀改":132,"衣笠改":15,"神鷹":8,"清霜改":24,"朝霜改二":39,"清霜改二":24,"霞改":50,"Iowa":11,"酒匂改":20,"千歳航改":3,"黒潮改二":12,"陸奥":11,"Atlanta改":85,"北上改二":84,"Atlanta":37,"Valiant改":56,"満潮改":44,"赤城":28,"初月改":90,"Z3 zwei":14,"千歳航":9,"長波改":36,"伊8":8,"占守改":42,"深雪改":68,"朝潮改":20,"伊41改":14,"伊400":9,"山城改二":5,"白雲改":30,"涼波改":97,"伊36":8,"扶桑改二":48,"磯波改":25,"大東改":18,"Fletcher改":45,"能美改":13,"第二十二号海防艦":31,"摩耶改二":31,"稲木改":43,"時津風改":19,"江風改二":17,"巻波改":22,"長波":14,"夕雲":13,"Luigi Torelli改":13,"鵜来":42,"風雲改二":27,"春風改":16,"Victorious改":67,"球磨改":24,"Javelin":39,"大鷹改":21,"神鷹改二":31,"伊19":28,"谷風":4,"Richelieu":22,"Intrepid":34,"海風改":18,"Bismarck zwei":4,"初霜改二":34,"狭霧改":23,"大潮改":16,"雪風":10,"長良改":10,"羽黒改二":55,"阿賀野":7,"Ark Royal":28,"千代田甲":38,"瑞穂改":47,"G.Garibaldi":5,"玉波改二":47,"早波":22,"不知火改二":35,"満潮":14,"Jervis改":57,"曙改":44,"鈴谷航改二":40,"能代":16,"Maestrale改":12,"日振改":17,"長月改":16,"Scirocco改":15,"山風改二丁":38,"風雲改":20,"第百一号輸送艦改":52,"鳳翔改二戦":18,"龍鳳":36,"Houston改":9,"迅鯨":27,"加賀":25,"倉橋":6,"夕雲改":10,"Октябрьская революция":19,"Honolulu改":8,"Massachusetts改":23,"荒潮改":9,"神通改":3,"Janus改":22,"狭霧":10,"鬼怒改":7,"利根":2,"荒潮改二":15,"速吸改":15,"阿賀野改":47,"初春改":8,"望月改":23,"Grecale":7,"Aquila改":30,"朝霜改二補":7,"巻雲改二":22,"五十鈴改":17,"平戸改":19,"三日月改":24,"那智改":8,"早霜":3,"千代田航改二":32,"Minneapolis":39,"瑞鶴":28,"文月改":22,"磯風乙改":23,"Prinz Eugen":67,"皐月改":21,"Samuel B.Roberts":25,"青葉改":5,"長鯨改":55,"早霜改":31,"天龍改二":18,"涼風":4,"Conte di Cavour nuovo":28,"神威改母":29,"御蔵":8,"Brooklyn":21,"比叡":11,"藤波":13,"青葉":3,"沖波改":28,"Langley":17,"榧":19,"浜波":17,"桃改":18,"卯月":9,"山風改":30,"衣笠":10,"Ташкент改":83,"伊201":63,"五十鈴":14,"親潮改二":18,"白雪改二":37,"沖波":6,"飛鷹":5,"能美":16,"Colorado改":28,"時雨":12,"Samuel B.Roberts Mk.II":28,"Pola改":19,"隼鷹":6,"神鷹改":18,"佐渡":8,"Perth改":11,"若葉改":13,"Littorio":14,"漣":2,"吹雪":30,"梅":14,"大井改":35,"大淀":10,"初春":5,"杉":17,"阿武隈":5,"Sheffield改":18,"国後":10,"大井改二":40,"Sheffield":21,"伊168":30,"岸波":4,"Colorado":7,"最上改二":16,"清霜":6,"Janus":16,"雲鷹改二":34,"多摩改二":22,"海風改二":31,"菊月改":12,"Z3改":14,"薄雲改":13,"鬼怒改二":22,"春日丸":7,"Gloire":30,"親潮改":9,"Z1":33,"雷改":12,"有明":9,"葛城改":28,"有明改":14,"不知火":9,"曙":13,"大鳳":28,"Perth":8,"松":2,"島風":8,"鈴谷改":22,"霧島改":16,"熊野航改二":31,"Z1改":14,"昭南":16,"山風":7,"Jervis":50,"General Belgrano":17,"伊勢":4,"愛宕改":7,"伊41":7,"白雲":6,"古鷹改二":12,"屋代改":12,"鳥海":14,"大鷹":11,"弥生改":36,"龍田":3,"初風改":6,"神威改":8,"響改":34,"朝潮改二":22,"雲龍":6,"山風改二":32,"Rodney":17,"野分":10,"川内":5,"山城":4,"五月雨改":34,"朧":7,"Graf Zeppelin":17,"龍田改":21,"Brooklyn改":18,"Eidsvold":21,"高波":15,"羽黒改":12,"龍驤":4,"Commandant Teste":39,"山城改":19,"谷風丁改":10,"高波改":30,"酒匂":4,"浦波改二":17,"木曾改":6,"摩耶改":13,"山雲改":12,"舞風改":10,"C.Cappellini":10,"隼鷹改":26,"龍驤改":12,"Victorious":25,"De Ruyter":8,"涼波改二補":31,"潮改":13,"Italia":15,"比叡改二":33,"弥生":4,"伊26改":12,"山雲":1,"竹改":17,"Luigi Torelli":9,"岸波改":9,"Massachusetts":16,"早潮":6,"Houston":6,"涼月":18,"霰改":13,"石垣":5,"Samuel B.Roberts改":29,"皐月":5,"秋霜":11,"由良":4,"伊14":6,"敷波改二":28,"涼波":10,"初霜":3,"御蔵改":10,"占守":16,"深雪":2,"稲木":31,"G.Garibaldi改":16,"羽黒":6,"夕立改":9,"菊月":2,"皐月改二":44,"金剛":11,"鈴谷":3,"Roma改":30,"黒潮改":15,"南海":37,"South Dakota":5,"Гангут":10,"黒潮":5,"暁":2,"夕張":12,"梅改":18,"若葉":5,"松改":9,"佐渡改":14,"伊58":20,"Lexington":4,"Гангут два":23,"千代田":7,"加古改":4,"Nelson":24,"霰改二":11,"陽炎改":16,"祥鳳":4,"福江":8,"Drum":15,"香取":4,"電":2,"八丈":12,"叢雲改":21,"秋雲":5,"Zara改":13,"大井":9,"陽炎改二":17,"最上":5,"Nevada":17,"磯波改二":6,"足柄改二":19,"阿武隈改":13,"霧島":8,"倉橋改":17,"天龍":3,"那珂改二":10,"U-511":5,"Conte di Cavour改":3,"綾波":5,"江風":8,"春風":5,"夕暮改":13,"Scirocco":7,"朝潮":4,"De Ruyter改":5,"L.d.S.D.d.Abruzzi改":17,"霞":13,"竹":7,"朝雲改":6,"五月雨":3,"三日月":9,"敷波改":9,"古鷹改":4,"不知火改":13,"大東":9,"Bismarck":17,"白雪":8,"L.d.S.D.d.Abruzzi":11,"浜風":5,"Jean Bart":13,"霰":5,"長良":2,"Honolulu":14,"伊13":3,"那智改二":9,"松風":2,"初雪":3,"涼風改":12,"択捉":7,"朝霜改":15,"平安丸":10,"夕立":6,"愛宕":3,"千代田航改":6,"高雄改":5,"神通":7,"陽炎":6,"長波改二補":13,"親潮":6,"榛名":4,"摩耶":2,"木曾":6,"照月":2,"叢雲":4,"響":3,"屋代":4,"熊野":2,"天城":3,"松風改":9,"加古改二":3,"筑摩改":5,"望月":5,"Aquila":8,"C.Cappellini改":5,"夏雲改":7,"春雨":4,"葛城":1,"天霧改二":12,"荒潮":2,"日進改":1,"筑摩改二":2,"那珂":3,"日振":8,"筑摩":2,"白露":2,"足柄改":2,"Maryland":4,"衣笠改二":10,"木曾改二":13,"扶桑改":9,"文月":1,"Pola":1,"日進":1,"多摩改":8,"Libeccio":2,"Salmon":2,"那珂改":2,"Helena":2,"巻雲":1,"朝雲":1,"秋津洲":3,"村雨":3,"Hornet":13,"扶桑":1,"古鷹":2,"峯雲":2,"敷波":1,"子日":2,"Conte di Cavour":1,"水無月":4,"鬼怒":3,"大潮":3,"Z3":4,"時津風":3,"足柄":1,"千代田改":2,"睦月":2,"浦波":1,"長月":1,"名取":1,"那智":1,"多摩":1,"嵐":1,"千歳改":2,"日向":1,"高雄":1},"kdockCount":{"2":32990,"3":11473,"4":8122},"rate":1.989},{"recipe":[999,999,30,30,1],"count":2,"usedCount":131,"hqLvCount":{"120":2},"secretaryCount":{"瑞鶴改二甲":1,"Heywood L.E.改":1},"kdockCount":{"4":1,"2":1},"rate":1.527},{"recipe":[30,30,530,30,1],"count":1,"usedCount":15,"hqLvCount":{"120":1},"secretaryCount":{"伊201改":1},"kdockCount":{"2":1},"rate":6.667},{"recipe":[31,32,33,34,1],"count":1,"usedCount":1,"hqLvCount":{"120":1},"secretaryCount":{"Glorious":1},"kdockCount":{"2":1},"rate":100.0},{"recipe":[30,130,30,30,1],"count":5,"usedCount":147,"hqLvCount":{"90":1,"120":4},"secretaryCount":{"伊勢改":1,"明石改":4},"kdockCount":{"2":1,"3":2,"4":2},"rate":3.401},{"recipe":[130,130,130,130,1],"count":7,"usedCount":311,"hqLvCount":{"120":6,"119":1},"secretaryCount":{"熊野航改二":1,"翔鶴改二甲":4,"夕張改二特":1,"鳳翔改":1},"kdockCount":{"2":3,"3":2,"4":2},"rate":2.251},{"recipe":[30,30,200,30,1],"count":1,"usedCount":23,"hqLvCount":{"120":1},"secretaryCount":{"Langley改":1},"kdockCount":{"2":1},"rate":4.348},{"recipe":[30,30,130,30,1],"count":7,"usedCount":150,"hqLvCount":{"120":4,"1":1,"117":2},"secretaryCount":{"涼月改":1,"大和改二":1,"潮":1,"霧島改二":2,"朝風改":1,"浜波改二":1},"kdockCount":{"3":1,"2":4,"4":2},"rate":4.667},{"recipe":[400,600,30,30,1],"count":5,"usedCount":144,"hqLvCount":{"6":1,"98":1,"46":1,"113":1,"110":1},"secretaryCount":{"電":1,"金剛改二":1,"榛名改":1,"榛名改二":1,"曙改":1},"kdockCount":{"2":3,"3":1,"4":1},"rate":3.472},{"recipe":[30,230,30,230,1],"count":1,"usedCount":2,"hqLvCount":{"120":1},"secretaryCount":{"Hornet改":1},"kdockCount":{"3":1},"rate":50.0},{"recipe":[999,30,30,30,1],"count":3,"usedCount":233,"hqLvCount":{"120":3},"secretaryCount":{"赤城改二":1,"秋月改":1,"山風改二丁":1},"kdockCount":{"4":2,"2":1},"rate":1.288},{"recipe":[130,130,130,30,1],"count":3,"usedCount":187,"hqLvCount":{"120":3},"secretaryCount":{"矢矧改二乙":1,"夕雲改二":1,"飛龍改二":1},"kdockCount":{"4":1,"3":2},"rate":1.604},{"recipe":[30,30,150,150,1],"count":1,"usedCount":2,"hqLvCount":{"120":1},"secretaryCount":{"明石改":1},"kdockCount":{"2":1},"rate":50.0},{"recipe":[230,230,230,230,1],"count":1,"usedCount":43,"hqLvCount":{"120":1},"secretaryCount":{"Bismarck drei":1},"kdockCount":{"2":1},"rate":2.326},{"recipe":[30,30,30,999,1],"count":5,"usedCount":311,"hqLvCount":{"120":4,"106":1},"secretaryCount":{"Zara due":1,"武蔵改二":1,"山汐丸":1,"秋月改":1,"神州丸":1},"kdockCount":{"2":3,"4":2},"rate":1.608},{"recipe":[31,31,31,31,1],"count":4,"usedCount":79,"hqLvCount":{"120":2,"116":1,"96":1},"secretaryCount":{"夕張改二特":2,"Brooklyn":1,"利根改":1},"kdockCount":{"2":4},"rate":5.063},{"recipe":[30,100,30,30,1],"count":1,"usedCount":5,"hqLvCount":{"112":1},"secretaryCount":{"Samuel B.Roberts改":1},"kdockCount":{"2":1},"rate":20.0},{"recipe":[30,130,130,30,1],"count":3,"usedCount":66,"hqLvCount":{"120":2,"109":1},"secretaryCount":{"大和改二":1,"明石改":2},"kdockCount":{"2":2,"3":1},"rate":4.545},{"recipe":[100,110,100,100,1],"count":1,"usedCount":1,"hqLvCount":{"99":1},"secretaryCount":{"夕立改二":1},"kdockCount":{"2":1},"rate":100.0},{"recipe":[30,999,30,30,1],"count":13,"usedCount":422,"hqLvCount":{"71":2,"91":1,"120":9,"78":1},"secretaryCount":{"第四号海防艦":3,"陸奥改":1,"瑞鶴改二甲":2,"Thonburi改":1,"鹿島改":2,"涼波":1,"日振改":1,"香取改":1,"明石改":1},"kdockCount":{"2":10,"4":2,"3":1},"rate":3.081},{"recipe":[250,30,150,30,1],"count":1,"usedCount":6,"hqLvCount":{"109":1},"secretaryCount":{"明石改":1},"kdockCount":{"2":1},"rate":16.667},{"recipe":[120,230,330,30,1],"count":1,"usedCount":3,"hqLvCount":{"120":1},"secretaryCount":{"時雨改三":1},"kdockCount":{"2":1},"rate":33.333},{"recipe":[230,30,250,30,1],"count":1,"usedCount":70,"hqLvCount":{"70":1},"secretaryCount":{"響改":1},"kdockCount":{"2":1},"rate":1.429},{"recipe":[30,30,400,400,1],"count":1,"usedCount":1,"hqLvCount":{"85":1},"secretaryCount":{"明石":1},"kdockCount":{"3":1},"rate":100.0},{"recipe":[30,251,250,30,1],"count":1,"usedCount":25,"hqLvCount":{"120":1},"secretaryCount":{"Nelson改":1},"kdockCount":{"2":1},"rate":4.0},{"recipe":[100,100,200,30,1],"count":1,"usedCount":11,"hqLvCount":{"104":1},"secretaryCount":{"天津風改":1},"kdockCount":{"2":1},"rate":9.091},{"recipe":[100,30,100,30,1],"count":3,"usedCount":100,"hqLvCount":{"120":3},"secretaryCount":{"叢雲改二":2,"明石改":1},"kdockCount":{"2":2,"3":1},"rate":3.0},{"recipe":[230,30,200,30,1],"count":1,"usedCount":152,"hqLvCount":{"120":1},"secretaryCount":{"Northampton改":1},"kdockCount":{"2":1},"rate":0.658},{"recipe":[30,60,30,30,1],"count":1,"usedCount":13,"hqLvCount":{"69":1},"secretaryCount":{"飛鷹改":1},"kdockCount":{"2":1},"rate":7.692},{"recipe":[430,30,30,30,1],"count":1,"usedCount":15,"hqLvCount":{"120":1},"secretaryCount":{"大鳳改":1},"kdockCount":{"3":1},"rate":6.667},{"recipe":[30,999,999,30,1],"count":4,"usedCount":66,"hqLvCount":{"120":3,"71":1},"secretaryCount":{"翔鶴改二甲":1,"Glorious":1,"明石":1,"鹿島改":1},"kdockCount":{"2":3,"3":1},"rate":6.061},{"recipe":[30,34,30,30,1],"count":1,"usedCount":1,"hqLvCount":{"11":1},"secretaryCount":{"五十鈴改":1},"kdockCount":{"2":1},"rate":100.0},{"recipe":[30,31,31,30,1],"count":3,"usedCount":34,"hqLvCount":{"85":1,"120":2},"secretaryCount":{"白露改":1,"明石改":2},"kdockCount":{"2":3},"rate":8.824},{"recipe":[30,30,30,31,1],"count":2,"usedCount":132,"hqLvCount":{"120":2},"secretaryCount":{"明石改":1,"武蔵改二":1},"kdockCount":{"2":2},"rate":1.515},{"recipe":[30,250,200,30,1],"count":6,"usedCount":228,"hqLvCount":{"120":6},"secretaryCount":{"北上改二":4,"夕立改二":2},"kdockCount":{"2":2,"3":4},"rate":2.632},{"recipe":[31,30,30,31,1],"count":1,"usedCount":10,"hqLvCount":{"79":1},"secretaryCount":{"睦月改":1},"kdockCount":{"2":1},"rate":10.0},{"recipe":[100,100,100,100,1],"count":2,"usedCount":33,"hqLvCount":{"120":2},"secretaryCount":{"村雨改二":2},"kdockCount":{"2":2},"rate":6.061},{"recipe":[270,330,130,30,1],"count":1,"usedCount":25,"hqLvCount":{"85":1},"secretaryCount":{"Z1":1},"kdockCount":{"3":1},"rate":4.0},{"recipe":[30,31,30,30,1],"count":4,"usedCount":74,"hqLvCount":{"40":2,"120":2},"secretaryCount":{"伊203":2,"長門改二":2},"kdockCount":{"2":2,"3":2},"rate":5.405},{"recipe":[200,100,300,30,1],"count":1,"usedCount":51,"hqLvCount":{"102":1},"secretaryCount":{"Z1":1},"kdockCount":{"3":1},"rate":1.961},{"recipe":[40,40,40,40,1],"count":1,"usedCount":53,"hqLvCount":{"3":1},"secretaryCount":{"名取":1},"kdockCount":{"2":1},"rate":1.887},{"recipe":[230,230,230,30,1],"count":3,"usedCount":138,"hqLvCount":{"120":2,"108":1},"secretaryCount":{"Wasp改":1,"夕張改二特":1,"矢矧改二":1},"kdockCount":{"2":2,"4":1},"rate":2.174},{"recipe":[320,100,100,30,1],"count":1,"usedCount":1,"hqLvCount":{"1":1},"secretaryCount":{"龍田":1},"kdockCount":{"2":1},"rate":100.0},{"recipe":[250,30,30,230,1],"count":2,"usedCount":12,"hqLvCount":{"109":2},"secretaryCount":{"北上改":1,"青葉":1},"kdockCount":{"2":2},"rate":16.667},{"recipe":[230,30,230,30,1],"count":1,"usedCount":97,"hqLvCount":{"113":1},"secretaryCount":{"大和改二":1},"kdockCount":{"3":1},"rate":1.031},{"recipe":[30,40,30,30,1],"count":1,"usedCount":62,"hqLvCount":{"104":1},"secretaryCount":{"Saratoga":1},"kdockCount":{"2":1},"rate":1.613},{"recipe":[30,30,230,30,1],"count":5,"usedCount":74,"hqLvCount":{"120":5},"secretaryCount":{"村雨改二":1,"能代改二":1,"加賀改二":2,"伊19改":1},"kdockCount":{"2":2,"4":3},"rate":6.757},{"recipe":[250,200,30,30,1],"count":14,"usedCount":896,"hqLvCount":{"104":2,"41":1,"108":1,"47":1,"34":1,"116":1,"88":1,"105":1,"120":3,"101":1,"98":1},"secretaryCount":{"択捉":1,"祥鳳改":2,"大和改":1,"Z1":1,"千歳航":1,"Gambier Bay Mk.II":1,"武蔵":1,"Iowa改":1,"明石改":1,"赤城改二戊":2,"大和改二":1,"鈴谷改":1},"kdockCount":{"2":10,"3":3,"4":1},"rate":1.563},{"recipe":[200,30,200,30,1],"count":1,"usedCount":111,"hqLvCount":{"120":1},"secretaryCount":{"稲木改二":1},"kdockCount":{"2":1},"rate":0.901},{"recipe":[130,30,30,30,1],"count":1,"usedCount":41,"hqLvCount":{"120":1},"secretaryCount":{"山城改二":1},"kdockCount":{"2":1},"rate":2.439},{"recipe":[30,30,50,30,1],"count":1,"usedCount":23,"hqLvCount":{"103":1},"secretaryCount":{"赤城改":1},"kdockCount":{"2":1},"rate":4.348},{"recipe":[230,30,330,30,1],"count":1,"usedCount":9,"hqLvCount":{"120":1},"secretaryCount":{"天津風改":1},"kdockCount":{"4":1},"rate":11.111},{"recipe":[30,400,600,30,1],"count":1,"usedCount":15,"hqLvCount":{"112":1},"secretaryCount":{"榛名改二":1},"kdockCount":{"2":1},"rate":6.667},{"recipe":[200,30,250,30,1],"count":10,"usedCount":389,"hqLvCount":{"18":1,"16":1,"120":4,"21":1,"108":1,"8":1,"81":1},"secretaryCount":{"加賀":1,"夕立":1,"加賀改":2,"夕立改":1,"Z1":1,"鹿島改":1,"矢矧改二乙":2,"夕張":1},"kdockCount":{"2":6,"4":2,"3":2},"rate":2.571},{"recipe":[150,140,130,130,1],"count":1,"usedCount":2,"hqLvCount":{"120":1},"secretaryCount":{"翔鶴改二甲":1},"kdockCount":{"3":1},"rate":50.0},{"recipe":[130,30,130,30,1],"count":4,"usedCount":139,"hqLvCount":{"120":4},"secretaryCount":{"鵜来改":1,"矢矧改二乙":1,"明石改":1,"玉波改二":1},"kdockCount":{"2":3,"4":1},"rate":2.878},{"recipe":[30,30,110,30,1],"count":4,"usedCount":71,"hqLvCount":{"115":2,"120":2},"secretaryCount":{"白露改二":2,"神通改二":2},"kdockCount":{"2":4},"rate":5.634},{"recipe":[30,330,230,30,1],"count":1,"usedCount":2,"hqLvCount":{"120":1},"secretaryCount":{"能代改二":1},"kdockCount":{"2":1},"rate":50.0}]}