{"parse":{"title":"西方海域/4-5/带路条件","pageid":46749,"revid":182205,"wikitext":"{{Hide\n|标题=舰种缩写\n|内容=\n<ul>\n<li>[[BB]]系=[[BB]](包括大多数低速战舰)+[[BC]]/[[FBB]](巡洋战舰，包括全部高速战舰及甘古特)+[[BBV]](航空战舰)<br/>\n<li>[[CV]]系=[[CV]](正规空母)+[[CVB]](装甲空母)+[[CVL]](轻空母)+[[CVE]](护卫空母)<br/>\n<li>[[CA]]系=[[CA]](重巡洋舰)+[[CAV]](航空巡洋舰)<br/>\n<li>[[CL]]系=[[CL]](轻巡洋舰)+[[CLT]](重雷装巡洋舰)+[[CT]](练习巡洋舰)<br/>\n<li>[[DD]]=驱逐舰<br/>\n<li>[[DE]]=海防舰=[[DE]](海防舰)+[[CD]](海防战舰)<br/>\n<li>[[SS]]系=[[SS]](潜水舰)+[[SSV]](潜水空母)<br/>\n<li>[[AV]]=水上机母舰<br/>\n<li>[[AO]]=补给舰<br/>\n<li>[[LHA]]=扬陆舰<br/>\n<li>[[AS]]=潜水母舰<br/>\n<li>[[AR]]=工作舰<br/>\n</ul>\n}}<table style='text-align: left' class='wikitable'  ><tr> <td>分歧点</td> <td>条件</td> </tr><tr> <td><b>出发点</b></td><td><ul><li>50%去A，50%去C<br/></ul></td> </tr><tr> <td><b><span style=\"color:red\">E</span></b></td><td><ul><span style=\"color:skyblue\">高速+</span>、<span style=\"color:royalblue\">最速</span>舰队 去M<br/><li>AO&gt;=1 去M<br/><li>BB系+CV系&gt;=3 去M<br/><li>CL&gt;=1 且 DD+DE&gt;=2 去M<br/><li>其余去K<br/></ul></td> </tr><tr> <td><b><span style=\"color:red\">G</span></b></td><td><ul><span style=\"color:skyblue\">高速+</span>、<span style=\"color:royalblue\">最速</span>舰队 去H<br/><li>BB系+CV系&gt;=4 去D<br/><li>DD+DE&gt;=2 去H<br/><li>其余随机去D/H？<br/></ul></td> </tr><tr> <td><b><span style=\"color:crimson\">H</span></b></td><td><ul><li><span style=\"color:skyblue\">高速+</span>、<span style=\"color:royalblue\">最速</span>舰队 且 BB系+CV系&lt;=4 去T<br/><li>CL&gt;=1 且 DD+DE&gt;=3 去T<br/><li>CL&gt;=1 且 DD+DE=2 且 经过F点的舰队 去T<br/><li>其余去K<br/></ul></td> </tr><tr> <td><b><span style=\"color:red\">K</span></b></td><td><ul><li>BB系+CV+CVB&gt;=4 去M<br/><li>BB系+CV系&gt;=5 去M<br/><li>经过E点的舰队<br/><ul><li>DD+DE&lt;=1 去M<br/><li>DD+DE&gt;=2 随机去M<br/></ul><li>SS系&gt;=1 随机去M<br/><li>分歧点系数=2<br/>索敌&gt;=70 去T(司令部系数0.35，索敌&gt;=76)<br/>索敌60~70 随机去T，索敌越高去T概率越高<br/>索敌&lt;60 去L<br/></ul></td> </tr><tr> <td><b><span style=\"color:skyblue\">M</span></b></td><td><ul><li><span style=\"color:royalblue\">最速</span>舰队 去N<br/><li>DD&lt;=1 去R<br/><li>低速舰队 去R<br/><li><span style=\"color:skyblue\">高速+</span>舰队 去N<br/><li>BB系+CV+CVB&lt;=1 去N<br/><li>BB系+CV+CVB&gt;=2 去R<br/></ul></td> </tr><tr> <td><b><span style=\"color:red\">O</span></b></td><td><ul><li>低速舰队 且 CAV&lt;=1 去N<br/><li>其余随机去N/T(重舰队去N概率较高)<br/></ul></td> </tr><tr> <td><b><span style=\"color:skyblue\">Q</span></b></td><td><ul><li>分歧点系数=2<br/>索敌&lt;50 去P<br/>索敌50~60 随机去P<br/><li>去P判定失败 或索敌&gt;=60(司令部系数0.35，索敌&gt;=66)<br/><ul><li>BB系+CV系&gt;=5 去O<br/><li>DD=0 去O<br/><li>其余去N<br/></ul></ul></td> </tr><tr> <td><b><span style=\"color:purple\">R</span></b></td><td><ul><li><span style=\"color:skyblue\">高速+</span>舰队 去N<br/><li>低速舰队 去S<br/><li>DD&lt;=1 去S<br/><li>CAV+CL+AV=0 去S<br/><li>其余去N<br/></ul></td> </tr></table><div>转自nga梦美:https://bbs.nga.cn/read.php?pid=330616096</div>"}}